{
  "type": "script",
  "seleniumVersion": "2",
  "formatVersion": 2,
  "steps": [
    {
      "type": "get",
      "url": "http://www.theprogrampdx.com/"
    },
    {
      "type": "clickElement",
      "step_name": "2.",
      "locator": {
        "type": "css selector",
        "value": "circle.play-btn-circle"
      }
    },
    {
      "type": "assertElementPresent",
      "locator": {
        "type": "css selector",
        "value": "h2.italic.fade"
      }
    },
    {
      "type": "verifyElementPresent",
      "locator": {
        "type": "xpath",
        "value": "//section[@class='brand-partners-section']//h2[.='Brand Partners']"
      }
    },
    {
      "type": "verifyElementPresent",
      "locator": {
        "type": "xpath",
        "value": "//section[@class='brand-partners-section']/div/div[2]/img"
      }
    },
    {
      "type": "clickElement",
      "locator": {
        "type": "xpath",
        "value": "//section[6]/div[1]/a/div[2]/div/h2"
      }
    },
    {
      "type": "get",
      "url": "http://www.theprogrampdx.com/"
    },
    {
      "type": "clickElement",
      "locator": {
        "type": "xpath",
        "value": "//section[6]/div[2]/a/div[2]/div/h2"
      }
    },
    {
      "type": "get",
      "url": "http://www.theprogrampdx.com/"
    },
    {
      "type": "clickElement",
      "locator": {
        "type": "xpath",
        "value": "//section[6]/div[3]/a/div[2]/div/h2"
      }
    },
    {
      "type": "get",
      "url": "http://www.theprogrampdx.com/"
    },
    {
      "type": "clickElement",
      "locator": {
        "type": "xpath",
        "value": "//section[6]/div[4]/a/div[2]/div/h2"
      }
    },
    {
      "type": "get",
      "url": "http://www.theprogrampdx.com/"
    },
    {
      "type": "verifyText",
      "locator": {
        "type": "xpath",
        "value": "//section[@class='capabilities-section']//h2[.='Capabilities']"
      },
      "text": "Capabilities"
    },
    {
      "type": "assertElementPresent",
      "locator": {
        "type": "xpath",
        "value": "//section[@class='capabilities-section']/div/div[2]/div[2]/div[1]/img"
      }
    },
    {
      "type": "verifyText",
      "locator": {
        "type": "xpath",
        "value": "//section[@class='capabilities-section']//h3[.='Strategy']"
      },
      "text": "strategy"
    },
    {
      "type": "verifyText",
      "locator": {
        "type": "xpath",
        "value": "//section[@class='capabilities-section']/div/div[6]/div[2]/div[2]/p"
      },
      "text": "  We deliver immersive, sharable experiences that get people talking. Each touchpoint is meticulously planned to deliver maximal impact."
    },
    {
      "type": "verifyText",
      "locator": {
        "type": "xpath",
        "value": "//section[@class='capabilities-section']//li[.='Content']"
      },
      "text": "Content"
    },
    {
      "type": "verifyText",
      "locator": {
        "type": "xpath",
        "value": "//section[8]/div/h2"
      },
      "text": "We are thinkers, doers, builders, and ping-pongers."
    },
    {
      "type": "mouseOverElement",
      "locator": {
        "type": "css selector",
        "value": "h4.name"
      }
    },
    {
      "type": "verifyTextPresent",
      "text": "Ethan Smith-Gillespie"
    }
  ],
  "data": {
    "configs": {},
    "source": "none"
  },
  "inputs": [],
  "timeoutSeconds": 60
}